pulse_telemetry/__init__.py
pulse_telemetry/logging.py
pulse_telemetry/apps/__init__.py
pulse_telemetry/apps/table_maintenance.py
pulse_telemetry/apps/telemetry_statistics.py
pulse_telemetry/sparklib/__init__.py
pulse_telemetry/sparklib/iceberg.py
pulse_telemetry/sparklib/processing_incremental.py
pulse_telemetry/sparklib/statistics_cycle.py
pulse_telemetry/sparklib/statistics_step.py
pulse_telemetry/sparklib/telemetry.py
pulse_telemetry/utils/__init__.py
pulse_telemetry/utils/channel.py
pulse_telemetry/utils/telemetry_generator.py
pulse_telemetry-0.1.1.dist-info/LICENSE
pulse_telemetry-0.1.1.dist-info/METADATA
pulse_telemetry-0.1.1.dist-info/WHEEL
pulse_telemetry-0.1.1.dist-info/top_level.txt
pulse_telemetry-0.1.1.dist-info/RECORD
