Metadata-Version: 2.1
Name: pulse-telemetry
Version: 0.1.1
Summary: Spark applications for transforming raw incoming data into a set of schemas for analysis.
Author-email: Maxwell Dylla <maxwell.dylla@gmail.com>, Erik Amundson <erik0422@gmail.com>
License-File: LICENSE
Requires-Dist: pyspark ==3.5.1
Provides-Extra: dev
Requires-Dist: mypy ==1.10.1 ; extra == 'dev'
Requires-Dist: pandas ==2.2.3 ; extra == 'dev'
Requires-Dist: pytest ==8.2.2 ; extra == 'dev'
Requires-Dist: pytest-cov ==5.0.0 ; extra == 'dev'
Requires-Dist: ruff ==0.5.2 ; extra == 'dev'
Requires-Dist: setuptools ==75.1.0 ; extra == 'dev'
